raschietto/__init__.py
raschietto-0.2.0.dist-info/METADATA
raschietto-0.2.0.dist-info/RECORD
raschietto-0.2.0.dist-info/WHEEL
raschietto-0.2.0.dist-info/top_level.txt
