Metadata-Version: 2.1
Name: raschietto
Version: 0.2.0
Summary: A simple web scraping library
Home-page: https://gitlab.com/matteo-ronchetti/raschietto
Author: Matteo Ronchetti
Author-email: matteo@ronchetti.xyz
License: UNKNOWN
Keywords: scraping,web
Platform: UNKNOWN
Classifier: Programming Language :: Python :: 3
Requires-Dist: lxml (==4.2.5)
Requires-Dist: cssselect (==1.0.3)
Requires-Dist: requests (==2.20.1)
Requires-Dist: urllib3 (==1.24.1)
